octopus_energy_api/__init__.py
octopus_energy_api/account.py
octopus_energy_api/api_interface.py
octopus_energy_api/octopus_energy_api.py
octopus_energy_api/urls.py
octopus_energy_api-0.8.dist-info/METADATA
octopus_energy_api-0.8.dist-info/WHEEL
octopus_energy_api-0.8.dist-info/top_level.txt
octopus_energy_api-0.8.dist-info/RECORD
