Metadata-Version: 2.1
Name: octopus-energy-api
Version: 0.8
Summary: Wrapper for communicating with the Octopus Energy API
Home-page: https://github.com/euanacampbell/octopus_energy_api
Author: Euan Campbell
Author-email: dev@euan.app
License: MIT
Download-URL: https://github.com/euanacampbell/octopus_energy_api/archive/refs/heads/master.tar.gz
Keywords: energy,api,requests
Platform: UNKNOWN
Classifier: Development Status :: 3 - Alpha
Classifier: Intended Audience :: Developers
Classifier: Topic :: Software Development :: Build Tools
Classifier: License :: OSI Approved :: MIT License
Classifier: Programming Language :: Python :: 3
Classifier: Programming Language :: Python :: 3.4
Classifier: Programming Language :: Python :: 3.5
Classifier: Programming Language :: Python :: 3.6
Requires-Dist: requests
